elastic_stacker/__about__.py
elastic_stacker/__init__.py
elastic_stacker/stacker.py
elastic_stacker/elasticsearch/component_templates.py
elastic_stacker/elasticsearch/enrich_policies.py
elastic_stacker/elasticsearch/index_templates.py
elastic_stacker/elasticsearch/indices.py
elastic_stacker/elasticsearch/pipelines.py
elastic_stacker/elasticsearch/role_mappings.py
elastic_stacker/elasticsearch/roles.py
elastic_stacker/elasticsearch/transforms.py
elastic_stacker/elasticsearch/watches.py
elastic_stacker/kibana/agent_policies.py
elastic_stacker/kibana/package_policies.py
elastic_stacker/kibana/saved_objects.py
elastic_stacker/utils/client.py
elastic_stacker/utils/config.py
elastic_stacker/utils/controller.py
elastic_stacker/utils/logging.py
elastic_stacker/utils/schemas.py
elastic_stacker-0.3.3.dist-info/METADATA
elastic_stacker-0.3.3.dist-info/WHEEL
elastic_stacker-0.3.3.dist-info/entry_points.txt
elastic_stacker-0.3.3.dist-info/licenses/LICENSE
elastic_stacker-0.3.3.dist-info/RECORD
