Metadata-Version: 2.4
Name: elastic-stacker
Version: 0.3.3
Summary: Import/export tool for the Elastic Stack.
Project-URL: repository, https://github.com/llnl/elastic-stacker
Author-email: James Taliaferro <taliaferro1+pypi@llnl.gov>
License: Apache License
License-File: LICENSE
Keywords: elasticsearch
Classifier: License :: OSI Approved :: Apache Software License
Requires-Python: >=3.9
Requires-Dist: ecs-logging>=2.2.0
Requires-Dist: fire>=0.7.0
Requires-Dist: httpx>=0.27.2
Requires-Dist: marshmallow>=3.23.0
Requires-Dist: python-slugify>=8.0.4
Requires-Dist: pyyaml>=6.0.2
